ruminate/__init__.py
ruminate/admin_urls.py
ruminate/apps.py
ruminate/blocks.py
ruminate/default_settings.py
ruminate/html_to_text.py
ruminate/model_admin.py
ruminate/model_fields.py
ruminate/model_porter.py
ruminate/models.py
ruminate/preview.py
ruminate/side_panels.py
ruminate/tests.py
ruminate/wagtail_hooks.py
ruminate/wagtail_settings.py
ruminate/migrations/0001_initial.py
ruminate/migrations/__init__.py
ruminate/static/ruminate/css/fonts.css
ruminate/static/ruminate/css/ruminate_admin.css
ruminate/static/ruminate/css/text.css
ruminate/templates/ruminate/article.html
ruminate/templates/ruminate/article_endnotes.html
ruminate/templates/ruminate/article_index_page.html
ruminate/templates/ruminate/article_page.html
ruminate/templates/ruminate/article_preview.html
ruminate/templates/ruminate/base_page.html
ruminate/templates/ruminate/blocks/article_block.html
ruminate/templates/ruminate/blocks/article_boilerplate.html
ruminate/templates/ruminate/blocks/article_boilerplate_block.html
ruminate/templates/ruminate/blocks/article_content_block.html
ruminate/templates/ruminate/blocks/article_references_block.html
ruminate/templates/ruminate/blocks/article_tags_block.html
ruminate/templates/ruminate/blocks/minimal_intro_block.html
ruminate/templates/ruminate/blocks/none_intro_block.html
ruminate/templates/ruminate/blocks/note_block.html
ruminate/templates/ruminate/blocks/person_block.html
ruminate/templates/ruminate/blocks/preface_block.html
ruminate/templates/ruminate/blocks/section_block.html
ruminate/templates/ruminate/blocks/spread_intro_block.html
ruminate-4.1.1.dist-info/AUTHORS.txt
ruminate-4.1.1.dist-info/LICENSE.txt
ruminate-4.1.1.dist-info/METADATA
ruminate-4.1.1.dist-info/WHEEL
ruminate-4.1.1.dist-info/top_level.txt
ruminate-4.1.1.dist-info/zip-safe
ruminate-4.1.1.dist-info/RECORD
