Metadata-Version: 2.1
Name: ruminate
Version: 4.1.1
Summary: A Wagtail app for publishing article pages in an academic/scientifically-oriented setting.
Home-page: https://github.com/high-dimensional/ruminate
Author: High Dimensional Neurology Group, UCL
Author-email: pypi@highdimensional.net
License: BSD-3-Clause
Platform: any
Classifier: Framework :: Django
Classifier: Framework :: Wagtail
Classifier: Programming Language :: Python :: 3
Classifier: Programming Language :: Python :: 3.8
Classifier: License :: OSI Approved :: BSD License
Classifier: Operating System :: OS Independent
Requires-Python: >=3.8
License-File: LICENSE.txt
License-File: AUTHORS.txt
Requires-Dist: Django (<4.2,>=4.1)
Requires-Dist: wagtail (<4.2,>=4.1)
Requires-Dist: beautifulsoup4 (<4.12,>=4.11)
Requires-Dist: django-auxiliaries (<4.2,>=4.1)
Requires-Dist: model-porter (<4.2,>=4.1)
Requires-Dist: wagtail-block-model-field (<4.2,>=4.1)
Requires-Dist: wagtail-switch-block (<4.2,>=4.1)
Requires-Dist: wagtail-tags-block (<4.2,>=4.1)
Requires-Dist: wagtail-preference-blocks (<4.2,>=4.1)
Requires-Dist: wagtail-richer-text (<4.2,>=4.1)
Requires-Dist: draftail-maths (<4.2,>=4.1)
Requires-Dist: concisely (<4.2,>=4.1)
Requires-Dist: tour-guide (<4.2,>=4.1)
Requires-Dist: media-catalogue (<4.2,>=4.1.2)
Requires-Dist: wagtail-synopsis (<4.2,>=4.1)
Requires-Dist: officekit (<4.2,>=4.1)
Requires-Dist: bibster (<4.2,>=4.1)
Requires-Dist: figurative (<4.2,>=4.1)
Requires-Dist: swatchbook (<4.2,>=4.1)
Requires-Dist: morsels (<4.2,>=4.1)
